cccconverter/__init__.py
cccconverter/convert.py
cccconverter/parse_dict.py
cccconverter/spilt.py
cccconverter/dict/finals.csv
cccconverter/dict/initials.csv
cccconverter/dict/yuet_dict.csv
cccconverter_ostrichb-0.90.3.dist-info/METADATA
cccconverter_ostrichb-0.90.3.dist-info/WHEEL
cccconverter_ostrichb-0.90.3.dist-info/licenses/LICENSE.txt
cccconverter_ostrichb-0.90.3.dist-info/RECORD
