Metadata-Version: 2.1
Name: cccconverter_ostrichb
Version: 0.90.3
Summary: A Hong Kong Government Cantonese Romanisation converter
Project-URL: Homepage, https://github.com/Ostrichbeta/CCCConverter
Project-URL: Bug Tracker, https://github.com/Ostrichbeta/CCCConverterissues
Author-email: Ostrichbeta Chan <ostrichb@yandex.com>
License-File: LICENSE.txt
Classifier: License :: OSI Approved :: MIT License
Classifier: Operating System :: OS Independent
Classifier: Programming Language :: Python :: 3
Requires-Python: >=3.7
